odoo10_addon_crm_claim_rma_code-10.0.1.0.0.99.dev3-py2.7-nspkg.pth
odoo/addons/crm_claim_rma_code/README.rst
odoo/addons/crm_claim_rma_code/__init__.py
odoo/addons/crm_claim_rma_code/__manifest__.py
odoo/addons/crm_claim_rma_code/data/ir_sequence_type.xml
odoo/addons/crm_claim_rma_code/i18n/es.po
odoo/addons/crm_claim_rma_code/i18n/es_MX.po
odoo/addons/crm_claim_rma_code/i18n/es_PA.po
odoo/addons/crm_claim_rma_code/i18n/es_VE.po
odoo/addons/crm_claim_rma_code/models/__init__.py
odoo/addons/crm_claim_rma_code/models/crm_claim_type.py
odoo/addons/crm_claim_rma_code/static/description/icon.png
odoo/addons/crm_claim_rma_code/views/crm_claim_type.xml
odoo10_addon_crm_claim_rma_code-10.0.1.0.0.99.dev3.dist-info/DESCRIPTION.rst
odoo10_addon_crm_claim_rma_code-10.0.1.0.0.99.dev3.dist-info/METADATA
odoo10_addon_crm_claim_rma_code-10.0.1.0.0.99.dev3.dist-info/RECORD
odoo10_addon_crm_claim_rma_code-10.0.1.0.0.99.dev3.dist-info/WHEEL
odoo10_addon_crm_claim_rma_code-10.0.1.0.0.99.dev3.dist-info/metadata.json
odoo10_addon_crm_claim_rma_code-10.0.1.0.0.99.dev3.dist-info/namespace_packages.txt
odoo10_addon_crm_claim_rma_code-10.0.1.0.0.99.dev3.dist-info/top_level.txt
